LICENSE
README.md
setup.py
gitpump/__init__.py
gitpump/base.py
gitpump/constants.py
gitpump/describe_repo.py
gitpump/describe_user.py
gitpump/fetch_issues.py
gitpump/fetch_trending.py
gitpump/search_repo.py
gitpump/util.py
slackpump/__init__.py
slackpump/slack_client.py
slackpump/util.py
spider_nest.egg-info/PKG-INFO
spider_nest.egg-info/SOURCES.txt
spider_nest.egg-info/dependency_links.txt
spider_nest.egg-info/requires.txt
spider_nest.egg-info/top_level.txt
stackpump/__init__.py
stackpump/base.py
stackpump/fetch_questions.py
stackpump/util.py
web2markdown/__init__.py
web2markdown/base.py
web2markdown/dump_website.py
web2markdown/util.py
web2markdown/html2text/__init__.py
web2markdown/html2text/html2text.py
web2markdown/html2text/html2text_wrapper.py
web2markdown/usp/__about__.py
web2markdown/usp/__init__.py
web2markdown/usp/exceptions.py
web2markdown/usp/fetch_parse.py
web2markdown/usp/helpers.py
web2markdown/usp/log.py
web2markdown/usp/tree.py
web2markdown/usp/objects/__init__.py
web2markdown/usp/objects/page.py
web2markdown/usp/objects/sitemap.py
web2markdown/usp/web_client/__init__.py
web2markdown/usp/web_client/abstract_client.py
web2markdown/usp/web_client/requests_client.py