Metadata-Version: 2.1
Name: spider-nest
Version: 0.2.0
Summary: Tools to pull text data from github, slack, website, stackoverflow, etc.
Home-page: https://github.com/yhmo/spider-nest
Author: yihua.mo
Author-email: yihua.mo@zilliz.com
License: GPL v3.0
Classifier: Programming Language :: Python :: 3.7
Classifier: Programming Language :: Python :: 3.8
Classifier: Programming Language :: Python :: 3.9
Classifier: Programming Language :: Python :: 3.10
Classifier: Programming Language :: Python :: 3.11
Requires-Python: >=3.7
License-File: LICENSE
